<?xml version="1.0" encoding="windows-1250" ?><fullcourtgame><head><gamecode>isr-1680</gamecode><date>23/05/2013</date><home>2510811</home><away>251803</away><homename>Elizur Netaniya</homename><awayname>Hapoel Jerusalem</awayname><homescore>68</homescore><awayscore>79</awayscore><period>4</period><minute>40:00</minute><status>End of game</status><spectators></spectators><periodscores><pscore period="1" score="23-19" /><pscore period="2" score="16-20" /><pscore period="3" score="8-23" /><pscore period="4" score="21-17" /></periodscores></head><players side="1"><player code="A55148" name="DRAFIC Dolev" jersey="4" points="0" val="0" layupa="0" layupm="0" jumpera="0" jumperm="0" p3a="0" p3m="0" fta="0" ftm="0" orb="0" drb="0" trb="0" st="0" tov="0" foul="0" ff="0" ass="0" block="0" sr="0" min="01:45" starter="0" fga="0" fgm="0" p2a="0" p2m="0" p2p="0" p3p="0" layupp="0" jumperp="0" fgp="0" dunkp="0" dunka="0" dunkm="0" plusminus="-3" technikal="0" unsport="0" offfoul="0" deflections="0" /><player code="A59187" name="VALSENKO Tom" jersey="5" points="2" val="2" layupa="1" layupm="1" jumpera="0" jumperm="0" p3a="0" p3m="0" fta="0" ftm="0" orb="0" drb="0" trb="0" st="0" tov="0" foul="0" ff="0" ass="0" block="0" sr="0" min="00:30" starter="0" fga="1" fgm="1" p2a="1" p2m="1" p2p="100" p3p="0" layupp="100" jumperp="0" fgp="100" dunkp="0" dunka="0" dunkm="0" plusminus="0" technikal="0" unsport="0" offfoul="0" deflections="0" /><player code="A59188" name="LEVY Yonatan" jersey="7" points="0" val="1" layupa="0" layupm="0" jumpera="0" jumperm="0" p3a="0" p3m="0" fta="0" ftm="0" orb="0" drb="1" trb="1" st="0" tov="0" foul="0" ff="0" ass="0" block="0" sr="0" min="00:30" starter="0" fga="0" fgm="0" p2a="0" p2m="0" p2p="0" p3p="0" layupp="0" jumperp="0" fgp="0" dunkp="0" dunka="0" dunkm="0" plusminus="0" technikal="0" unsport="0" offfoul="0" deflections="0" /><player code="A55177" name="ZIKRI Segev" jersey="14" points="0" val="0" layupa="0" layupm="0" jumpera="0" jumperm="0" p3a="0" p3m="0" fta="0" ftm="0" orb="0" drb="0" trb="0" st="0" tov="0" foul="0" ff="0" ass="0" block="0" sr="0" min="00:30" starter="0" fga="0" fgm="0" p2a="0" p2m="0" p2p="0" p3p="0" layupp="0" jumperp="0" fgp="0" dunkp="0" dunka="0" dunkm="0" plusminus="2" technikal="0" unsport="0" offfoul="0" deflections="0" /><player code="A49418" name="SHULMAN Eyal" jersey="15" points="8" val="13" layupa="0" layupm="0" jumpera="1" jumperm="1" p3a="4" p3m="2" fta="0" ftm="0" orb="0" drb="0" trb="0" st="0" tov="0" foul="3" ff="3" ass="7" block="0" sr="0" min="24:15" starter="0" fga="1" fgm="1" p2a="1" p2m="1" p2p="100" p3p="50" layupp="0" jumperp="100" fgp="100" dunkp="0" dunka="0" dunkm="0" plusminus="-4" technikal="0" unsport="0" offfoul="0" deflections="0" /><player code="A36553" name="KILLINGSWORTH Marco" jersey="6" points="21" val="19" layupa="12" layupm="7" jumpera="1" jumperm="1" p3a="0" p3m="0" fta="8" ftm="5" orb="1" drb="4" trb="5" st="1" tov="3" foul="2" ff="6" ass="0" block="1" sr="2" min="35:15" starter="1" fga="13" fgm="8" p2a="13" p2m="8" p2p="62" p3p="0" layupp="58" jumperp="100" fgp="62" dunkp="0" dunka="0" dunkm="0" plusminus="-10" technikal="0" unsport="0" offfoul="0" deflections="0" /><player code="A08541" name="GUETA Eliran" jersey="9" points="0" val="-4" layupa="0" layupm="0" jumpera="0" jumperm="0" p3a="1" p3m="0" fta="0" ftm="0" orb="0" drb="1" trb="1" st="1" tov="0" foul="5" ff="0" ass="0" block="0" sr="0" min="10:15" starter="0" fga="0" fgm="0" p2a="0" p2m="0" p2p="0" p3p="0" layupp="0" jumperp="0" fgp="0" dunkp="0" dunka="0" dunkm="0" plusminus="0" technikal="0" unsport="0" offfoul="0" deflections="0" /><player code="A35678" name="ARIELY Tamir" jersey="10" points="0" val="-2" layupa="1" layupm="0" jumpera="0" jumperm="0" p3a="1" p3m="0" fta="0" ftm="0" orb="0" drb="0" trb="0" st="0" tov="0" foul="0" ff="0" ass="0" block="0" sr="0" min="02:15" starter="0" fga="1" fgm="0" p2a="1" p2m="0" p2p="0" p3p="0" layupp="0" jumperp="0" fgp="0" dunkp="0" dunka="0" dunkm="0" plusminus="-6" technikal="0" unsport="0" offfoul="0" deflections="0" /><player code="A14098" name="ORLAND Yehu" jersey="11" points="9" val="6" layupa="1" layupm="1" jumpera="2" jumperm="2" p3a="3" p3m="1" fta="0" ftm="0" orb="0" drb="0" trb="0" st="1" tov="1" foul="4" ff="1" ass="2" block="0" sr="0" min="28:15" starter="1" fga="3" fgm="3" p2a="3" p2m="3" p2p="100" p3p="33" layupp="100" jumperp="100" fgp="100" dunkp="0" dunka="0" dunkm="0" plusminus="-3" technikal="0" unsport="0" offfoul="0" deflections="0" /><player code="A43627" name="BRADLEY Ramel" jersey="12" points="14" val="14" layupa="6" layupm="2" jumpera="2" jumperm="1" p3a="3" p3m="1" fta="8" ftm="5" orb="2" drb="3" trb="5" st="4" tov="6" foul="4" ff="9" ass="3" block="0" sr="1" min="34:45" starter="1" fga="8" fgm="3" p2a="8" p2m="3" p2p="38" p3p="33" layupp="33" jumperp="50" fgp="38" dunkp="0" dunka="0" dunkm="0" plusminus="-17" technikal="0" unsport="0" offfoul="0" deflections="0" /><player code="A43412" name="WASHINGTON Deron" jersey="13" points="5" val="8" layupa="3" layupm="2" jumpera="1" jumperm="0" p3a="3" p3m="0" fta="2" ftm="1" orb="0" drb="5" trb="5" st="3" tov="2" foul="5" ff="2" ass="5" block="1" sr="0" min="30:00" starter="1" fga="4" fgm="2" p2a="4" p2m="2" p2p="50" p3p="0" layupp="67" jumperp="0" fgp="50" dunkp="100" dunka="1" dunkm="1" plusminus="-5" technikal="0" unsport="0" offfoul="0" deflections="0" /><player code="A38968" name="MORGAN Raymar" jersey="21" points="9" val="18" layupa="3" layupm="3" jumpera="2" jumperm="1" p3a="1" p3m="0" fta="2" ftm="1" orb="0" drb="8" trb="8" st="2" tov="3" foul="0" ff="2" ass="2" block="1" sr="0" min="31:45" starter="1" fga="5" fgm="4" p2a="5" p2m="4" p2p="80" p3p="0" layupp="100" jumperp="50" fgp="80" dunkp="0" dunka="0" dunkm="0" plusminus="-9" technikal="0" unsport="0" offfoul="0" deflections="0" /><player code="Team" name="Team" jersey="0" points="0" val="2" layupa="0" layupm="0" jumpera="0" jumperm="0" p3a="0" p3m="0" fta="0" ftm="0" orb="2" drb="0" trb="2" st="0" tov="0" foul="0" ff="0" ass="0" block="0" sr="0" min="00:00" starter="0" fga="0" fgm="0" p2a="0" p2m="0" p2p="0" p3p="0" layupp="0" jumperp="0" fgp="0" dunkp="0" dunka="0" dunkm="0" plusminus="0" technikal="0" unsport="0" offfoul="0" deflections="0" /></players><players side="0"><player code="A17053" name="LIMONAD Raviv Guy" jersey="5" points="14" val="17" layupa="3" layupm="2" jumpera="4" jumperm="3" p3a="1" p3m="0" fta="4" ftm="4" orb="1" drb="3" trb="4" st="3" tov="3" foul="2" ff="4" ass="0" block="0" sr="0" min="25:15" starter="1" fga="7" fgm="5" p2a="7" p2m="5" p2p="71" p3p="0" layupp="67" jumperp="75" fgp="71" dunkp="0" dunka="0" dunkm="0" plusminus="10" technikal="0" unsport="0" offfoul="0" deflections="0" /><player code="A47512" name="FELLS Courtney" jersey="7" points="11" val="15" layupa="2" layupm="2" jumpera="4" jumperm="1" p3a="2" p3m="1" fta="2" ftm="2" orb="1" drb="2" trb="3" st="2" tov="2" foul="1" ff="3" ass="3" block="0" sr="0" min="36:00" starter="1" fga="6" fgm="3" p2a="6" p2m="3" p2p="50" p3p="50" layupp="100" jumperp="25" fgp="50" dunkp="0" dunka="0" dunkm="0" plusminus="4" technikal="0" unsport="0" offfoul="0" deflections="0" /><player code="8192252" name="LIPHSHITZ Lior" jersey="9" points="0" val="-2" layupa="0" layupm="0" jumpera="0" jumperm="0" p3a="1" p3m="0" fta="0" ftm="0" orb="0" drb="0" trb="0" st="0" tov="1" foul="1" ff="0" ass="1" block="0" sr="0" min="07:30" starter="0" fga="0" fgm="0" p2a="0" p2m="0" p2p="0" p3p="0" layupp="0" jumperp="0" fgp="0" dunkp="0" dunka="0" dunkm="0" plusminus="12" technikal="0" unsport="0" offfoul="0" deflections="0" /><player code="A03385" name="TAPIRO Meir" jersey="12" points="2" val="5" layupa="0" layupm="0" jumpera="3" jumperm="1" p3a="0" p3m="0" fta="0" ftm="0" orb="0" drb="4" trb="4" st="0" tov="0" foul="3" ff="2" ass="2" block="0" sr="0" min="17:15" starter="0" fga="3" fgm="1" p2a="3" p2m="1" p2p="33" p3p="0" layupp="0" jumperp="33" fgp="33" dunkp="0" dunka="0" dunkm="0" plusminus="-6" technikal="0" unsport="0" offfoul="0" deflections="0" /><player code="A42652" name="DUNCAN Josh" jersey="15" points="23" val="32" layupa="10" layupm="5" jumpera="3" jumperm="0" p3a="4" p3m="4" fta="2" ftm="1" orb="1" drb="9" trb="10" st="2" tov="2" foul="3" ff="5" ass="5" block="1" sr="0" min="37:45" starter="1" fga="13" fgm="5" p2a="13" p2m="5" p2p="38" p3p="100" layupp="50" jumperp="0" fgp="38" dunkp="33" dunka="3" dunkm="1" plusminus="15" technikal="0" unsport="0" offfoul="0" deflections="0" /><player code="A49818" name="ARIEL Adam" jersey="4" points="0" val="0" layupa="0" layupm="0" jumpera="0" jumperm="0" p3a="0" p3m="0" fta="0" ftm="0" orb="0" drb="0" trb="0" st="0" tov="0" foul="0" ff="0" ass="0" block="0" sr="0" min="00:00" starter="0" fga="0" fgm="0" p2a="0" p2m="0" p2p="0" p3p="0" layupp="0" jumperp="0" fgp="0" dunkp="0" dunka="0" dunkm="0" plusminus="0" technikal="0" unsport="0" offfoul="0" deflections="0" /><player code="A49912" name="SAMUELS Samardo" jersey="8" points="11" val="7" layupa="7" layupm="3" jumpera="0" jumperm="0" p3a="0" p3m="0" fta="10" ftm="5" orb="1" drb="4" trb="5" st="0" tov="2" foul="5" ff="7" ass="0" block="1" sr="1" min="20:30" starter="0" fga="7" fgm="3" p2a="7" p2m="3" p2p="43" p3p="0" layupp="43" jumperp="0" fgp="43" dunkp="50" dunka="2" dunkm="1" plusminus="5" technikal="0" unsport="0" offfoul="0" deflections="0" /><player code="A46327" name="STEELE Ron" jersey="10" points="15" val="17" layupa="2" layupm="1" jumpera="1" jumperm="1" p3a="4" p3m="3" fta="2" ftm="2" orb="0" drb="1" trb="1" st="2" tov="1" foul="3" ff="1" ass="4" block="0" sr="0" min="35:15" starter="1" fga="3" fgm="2" p2a="3" p2m="2" p2p="67" p3p="75" layupp="50" jumperp="100" fgp="67" dunkp="0" dunka="0" dunkm="0" plusminus="13" technikal="0" unsport="0" offfoul="0" deflections="0" /><player code="A32730" name="KADIR Elishay" jersey="11" points="3" val="-5" layupa="4" layupm="1" jumpera="0" jumperm="0" p3a="0" p3m="0" fta="2" ftm="1" orb="1" drb="0" trb="1" st="1" tov="2" foul="5" ff="1" ass="1" block="1" sr="2" min="20:30" starter="1" fga="4" fgm="1" p2a="4" p2m="1" p2p="25" p3p="0" layupp="25" jumperp="0" fgp="25" dunkp="0" dunka="0" dunkm="0" plusminus="2" technikal="0" unsport="0" offfoul="0" deflections="0" /><player code="A35682" name="TAMIR Daniel" jersey="14" points="0" val="0" layupa="0" layupm="0" jumpera="0" jumperm="0" p3a="0" p3m="0" fta="0" ftm="0" orb="0" drb="0" trb="0" st="0" tov="0" foul="0" ff="0" ass="0" block="0" sr="0" min="00:00" starter="0" fga="0" fgm="0" p2a="0" p2m="0" p2p="0" p3p="0" layupp="0" jumperp="0" fgp="0" dunkp="0" dunka="0" dunkm="0" plusminus="0" technikal="0" unsport="0" offfoul="0" deflections="0" /><player code="A36404" name="GRUNFELD Dan" jersey="21" points="0" val="0" layupa="0" layupm="0" jumpera="0" jumperm="0" p3a="0" p3m="0" fta="0" ftm="0" orb="0" drb="0" trb="0" st="0" tov="0" foul="0" ff="0" ass="0" block="0" sr="0" min="00:00" starter="0" fga="0" fgm="0" p2a="0" p2m="0" p2p="0" p3p="0" layupp="0" jumperp="0" fgp="0" dunkp="0" dunka="0" dunkm="0" plusminus="0" technikal="0" unsport="0" offfoul="0" deflections="0" /><player code="Team" name="Team" jersey="0" points="0" val="4" layupa="0" layupm="0" jumpera="0" jumperm="0" p3a="0" p3m="0" fta="0" ftm="0" orb="3" drb="1" trb="4" st="0" tov="0" foul="0" ff="0" ass="0" block="0" sr="0" min="00:00" starter="0" fga="0" fgm="0" p2a="0" p2m="0" p2p="0" p3p="0" layupp="0" jumperp="0" fgp="0" dunkp="0" dunka="0" dunkm="0" plusminus="0" technikal="0" unsport="0" offfoul="0" deflections="0" /></players><teamstats><ts side="1" points="68" val="77" layupa="27" layupm="16" jumpera="9" jumperm="6" p3a="16" p3m="4" fta="20" ftm="12" orb="5" drb="22" trb="27" st="12" tov="15" foul="23" ff="23" ass="19" block="3" sr="3" min="200:00" fga="36" fgm="22" p2a="36" p2m="22" p2p="61" p3p="25" layupp="59" jumperp="67" fgp="61" dunkp="100" dunka="1" dunkm="1" plusminus="0" technikal="0" unsport="0" offfoul="0" deflections="0" timeouts="5" /><ts side="0" points="79" val="90" layupa="28" layupm="14" jumpera="15" jumperm="6" p3a="12" p3m="8" fta="22" ftm="15" orb="8" drb="24" trb="32" st="10" tov="13" foul="23" ff="23" ass="16" block="3" sr="3" min="200:00" fga="43" fgm="20" p2a="43" p2m="20" p2p="47" p3p="67" layupp="50" jumperp="40" fgp="47" dunkp="100" dunka="2" dunkm="2" plusminus="0" technikal="0" unsport="0" offfoul="0" deflections="0" timeouts="2" /></teamstats><filmlist><film id="2" fccode="1100" min="00:15" score="0-0"/><film id="27" min="00:15" side="1" fccode="1001" playercode="A17053" shottype="3" x="198" y="103" score="0-0"/><film id="28" min="00:15" side="0" fccode="1002" playercode="A43412" score="0-0"/><film id="29" fccode="1100" min="00:30" score="0-0"/><film id="30" fccode="1100" min="00:45" score="0-0"/><film id="31" min="00:45" side="0" fccode="1000" playercode="A36553" shottype="1" x="140" y="328" score="2-0"/><film id="32" fccode="1100" min="01:00" score="2-0"/><film id="33" min="01:00" side="0" fccode="1007" playercode="A43412" score="2-0"/><film id="34" min="01:00" side="1" fccode="1006" playercode="A47512" score="2-0"/><film id="35" min="01:00" side="1" fccode="1000" playercode="A47512" shottype="4" x="0" y="0" score="2-1"/><film id="36" min="01:00" side="1" fccode="1000" playercode="A47512" shottype="4" x="0" y="0" score="2-2"/><film id="37" fccode="1100" min="01:15" score="2-2"/><film id="38" min="01:15" side="0" fccode="1005" playercode="A43627" score="2-2"/><film id="39" fccode="1100" min="01:30" score="2-2"/><film id="40" min="01:30" side="1" fccode="1001" playercode="A32730" shottype="1" x="153" y="40" score="2-2"/><film id="41" min="01:30" side="1" fccode="1010" playercode="A32730" score="2-2"/><film id="42" min="01:30" side="0" fccode="1009" playercode="A36553" score="2-2"/><film id="43" min="01:30" side="0" fccode="1002" playercode="A36553" score="2-2"/><film id="44" fccode="1100" min="01:45" score="2-2"/><film id="45" min="01:45" side="0" fccode="1000" playercode="A38968" shottype="1" x="125" y="333" score="4-2"/><film id="46" min="01:45" side="0" fccode="1008" playercode="A43627" score="4-2"/><film id="47" fccode="1100" min="02:00" score="4-2"/><film id="52" min="02:00" side="1" fccode="1000" playercode="A42652" shottype="3" x="202" y="94" score="4-5"/><film id="53" min="02:00" side="1" fccode="1008" playercode="A46327" score="4-5"/><film id="54" fccode="1100" min="02:15" score="4-5"/><film id="55" min="02:15" side="0" fccode="1001" playercode="A43412" shottype="3" x="27" y="268" score="4-5"/><film id="56" min="02:15" side="1" fccode="1002" playercode="A17053" score="4-5"/><film id="57" fccode="1100" min="02:30" score="4-5"/><film id="58" min="02:30" side="1" fccode="1001" playercode="A17053" shottype="1" x="115" y="35" score="4-5"/><film id="59" min="02:30" side="0" fccode="1002" playercode="A38968" score="4-5"/><film id="60" min="02:30" side="0" fccode="1005" playercode="A43627" score="4-5"/><film id="61" min="02:30" side="1" fccode="1004" playercode="A32730" score="4-5"/><film id="62" fccode="1100" min="02:45" score="4-5"/><film id="63" min="02:45" side="1" fccode="1000" playercode="A46327" shottype="2" x="191" y="30" score="4-7"/><film id="64" fccode="1100" min="03:00" score="4-7"/><film id="65" min="03:00" side="0" fccode="1000" playercode="A43412" shottype="5" x="117" y="335" score="6-7"/><film id="66" min="03:00" side="0" fccode="1008" playercode="A38968" score="6-7"/><film id="67" fccode="1100" min="03:15" score="6-7"/><film id="68" min="03:15" side="0" fccode="1007" playercode="A14098" score="6-7"/><film id="69" min="03:15" side="1" fccode="1006" playercode="A17053" score="6-7"/><film id="70" fccode="1100" min="03:30" score="6-7"/><film id="71" min="03:30" side="1" fccode="1001" playercode="A42652" shottype="5" x="119" y="19" score="6-7"/><film id="72" min="03:30" side="0" fccode="1002" playercode="A38968" score="6-7"/><film id="73" fccode="1100" min="03:45" score="6-7"/><film id="74" min="03:45" side="0" fccode="1000" playercode="A38968" shottype="1" x="116" y="315" score="8-7"/><film id="75" fccode="1100" min="04:00" score="8-7"/><film id="80" min="04:00" side="1" fccode="1000" playercode="A17053" shottype="2" x="105" y="70" score="8-9"/><film id="81" fccode="1100" min="04:15" score="8-9"/><film id="82" fccode="1100" min="04:30" score="8-9"/><film id="83" min="04:30" side="0" fccode="1000" playercode="A14098" shottype="2" x="47" y="332" score="10-9"/><film id="84" min="04:30" side="0" fccode="1008" playercode="A43627" score="10-9"/><film id="85" fccode="1100" min="04:45" score="10-9"/><film id="86" min="04:45" side="1" fccode="1001" playercode="A46327" shottype="1" x="90" y="28" score="10-9"/><film id="87" min="04:45" side="0" fccode="1002" playercode="A43627" score="10-9"/><film id="88" min="04:45" side="0" fccode="1000" playercode="A14098" shottype="3" x="10" y="334" score="13-9"/><film id="89" min="04:45" side="0" fccode="1008" playercode="A43412" score="13-9"/><film id="90" fccode="1100" min="05:00" score="13-9"/><film id="91" fccode="1100" min="05:15" score="13-9"/><film id="92" min="05:15" side="1" fccode="1001" playercode="A32730" shottype="1" x="115" y="47" score="13-9"/><film id="93" min="05:15" side="0" fccode="1002" playercode="A38968" score="13-9"/><film id="94" min="05:15" side="0" fccode="1000" playercode="A36553" shottype="1" x="108" y="325" score="15-9"/><film id="95" min="05:15" side="0" fccode="1008" playercode="A43627" score="15-9"/><film id="96" fccode="1100" min="05:30" score="15-9"/><film id="97" fccode="1100" min="05:45" score="15-9"/><film id="98" min="05:45" side="1" fccode="1000" playercode="A42652" shottype="1" x="96" y="34" score="15-11"/><film id="99" fccode="1100" min="06:00" score="15-11"/><film id="104" min="06:00" side="1" fccode="1007" playercode="A32730" score="15-11"/><film id="105" min="06:00" side="0" fccode="1006" playercode="A38968" score="15-11"/><film id="106" min="06:00" side="1" fccode="1011" in="A49912" out="A32730" score="15-11"/><film id="107" min="06:00" side="0" fccode="1005" playercode="A36553" score="15-11"/><film id="108" min="06:00" side="1" fccode="1004" playercode="A42652" score="15-11"/><film id="109" min="06:00" side="1" fccode="1000" playercode="A42652" shottype="1" x="114" y="34" score="15-13"/><film id="110" fccode="1100" min="06:15" score="15-13"/><film id="111" fccode="1100" min="06:30" score="15-13"/><film id="112" min="06:30" side="1" fccode="1007" playercode="A49912" score="15-13"/><film id="113" min="06:30" side="0" fccode="1006" playercode="A36553" score="15-13"/><film id="114" min="06:30" side="0" fccode="1001" playercode="A36553" shottype="4" x="0" y="0" score="15-13"/><film id="115" min="06:30" side="0" fccode="1001" playercode="A36553" shottype="4" x="0" y="0" score="15-13"/><film id="116" min="06:30" side="1" fccode="1002" playercode="A42652" score="15-13"/><film id="117" fccode="1100" min="06:45" score="15-13"/><film id="118" min="06:45" side="1" fccode="1001" playercode="A42652" shottype="1" x="128" y="29" score="15-13"/><film id="119" min="06:45" side="0" fccode="1002" playercode="A38968" score="15-13"/><film id="120" fccode="1100" min="07:00" score="15-13"/><film id="121" min="07:00" side="0" fccode="1001" playercode="A14098" shottype="3" x="10" y="327" score="15-13"/><film id="122" min="07:00" side="1" fccode="1002" playercode="A49912" score="15-13"/><film id="123" fccode="1100" min="07:15" score="15-13"/><film id="124" min="07:15" side="1" fccode="1000" playercode="A47512" shottype="1" x="100" y="22" score="15-15"/><film id="125" fccode="1100" min="07:30" score="15-15"/><film id="126" min="07:30" side="0" fccode="1000" playercode="A43627" shottype="1" x="101" y="331" score="17-15"/><film id="127" fccode="1100" min="07:45" score="17-15"/><film id="128" min="07:45" side="1" fccode="1000" playercode="A49912" shottype="1" x="112" y="36" score="17-17"/><film id="129" fccode="1100" min="08:00" score="17-17"/><film id="134" fccode="1100" min="08:15" score="17-17"/><film id="135" min="08:15" side="0" fccode="1001" playercode="A43412" shottype="3" x="122" y="217" score="17-17"/><film id="136" min="08:15" side="0" fccode="1003" playercode="A36553" score="17-17"/><film id="137" fccode="1100" min="08:30" score="17-17"/><film id="138" min="08:30" side="0" fccode="1000" playercode="A36553" shottype="1" x="136" y="327" score="19-17"/><film id="139" fccode="1100" min="08:45" score="19-17"/><film id="140" fccode="1100" min="09:00" score="19-17"/><film id="141" min="09:00" side="1" fccode="1000" playercode="A17053" shottype="1" x="135" y="25" score="19-19"/><film id="142" min="09:00" side="1" fccode="1008" playercode="A46327" score="19-19"/><film id="143" min="09:00" side="0" fccode="1005" playercode="A43627" score="19-19"/><film id="144" min="09:00" side="1" fccode="1004" playercode="A46327" score="19-19"/><film id="145" fccode="1100" min="09:15" score="19-19"/><film id="146" min="09:15" side="1" fccode="1011" in="A03385" out="A46327" score="19-19"/><film id="147" min="09:15" side="0" fccode="1011" in="A49418" out="A43627" score="19-19"/><film id="148" min="09:15" side="0" fccode="1000" playercode="A38968" shottype="1" x="101" y="330" score="21-19"/><film id="149" min="09:15" side="0" fccode="1008" playercode="A49418" score="21-19"/><film id="150" fccode="1100" min="09:30" score="21-19"/><film id="151" fccode="1100" min="09:45" score="21-19"/><film id="152" min="09:45" side="1" fccode="1001" playercode="A49912" shottype="1" x="118" y="34" score="21-19"/><film id="153" min="09:45" side="0" fccode="1002" playercode="A43412" score="21-19"/><film id="154" min="09:45" side="1" fccode="1007" playercode="A03385" score="21-19"/><film id="155" min="09:45" side="0" fccode="1006" playercode="A49418" score="21-19"/><film id="156" min="09:45" side="1" fccode="1011" in="A32730" out="A42652" score="21-19"/><film id="157" min="09:45" side="0" fccode="1000" playercode="A49418" shottype="2" x="49" y="310" score="23-19"/><film id="158" fccode="1100" min="10:00" score="23-19"/><film id="163" fccode="1101" period="4" min="10:00" score="23-19"/><film id="168" min="10:00" side="1" fccode="1011" in="A46327" out="A17053" score="23-19"/><film id="169" min="10:00" side="1" fccode="1011" in="A42652" out="A32730" score="23-19"/><film id="170" fccode="1100" min="10:15" score="23-19"/><film id="171" min="10:15" side="0" fccode="1000" playercode="A14098" shottype="2" x="52" y="279" score="25-19"/><film id="172" min="10:15" side="0" fccode="1008" playercode="A43412" score="25-19"/><film id="173" fccode="1100" min="10:30" score="25-19"/><film id="174" min="10:30" side="1" fccode="1000" playercode="A46327" shottype="3" x="163" y="125" score="25-22"/><film id="175" fccode="1100" min="10:45" score="25-22"/><film id="176" min="10:45" side="0" fccode="1000" playercode="A36553" shottype="1" x="104" y="325" score="27-22"/><film id="177" min="10:45" side="0" fccode="1008" playercode="A49418" score="27-22"/><film id="178" min="10:45" side="0" fccode="1007" playercode="A49418" score="27-22"/><film id="179" min="10:45" side="1" fccode="1006" playercode="A03385" score="27-22"/><film id="180" fccode="1100" min="11:00" score="27-22"/><film id="181" min="11:00" side="1" fccode="1000" playercode="A03385" shottype="2" x="162" y="57" score="27-24"/><film id="182" fccode="1100" min="11:15" score="27-24"/><film id="183" min="11:15" side="0" fccode="1000" playercode="A49418" shottype="3" x="180" y="241" score="30-24"/><film id="184" min="11:15" side="0" fccode="1008" playercode="A14098" score="30-24"/><film id="185" fccode="1100" min="11:30" score="30-24"/><film id="186" min="11:30" side="1" fccode="1000" playercode="A49912" shottype="1" x="109" y="34" score="30-26"/><film id="187" fccode="1100" min="11:45" score="30-26"/><film id="188" min="11:45" side="0" fccode="1005" playercode="A38968" score="30-26"/><film id="189" min="11:45" side="1" fccode="1004" playercode="A47512" score="30-26"/><film id="190" min="11:45" side="1" fccode="1000" playercode="A42652" shottype="1" x="133" y="23" score="30-28"/><film id="191" min="11:45" side="1" fccode="1008" playercode="A47512" score="30-28"/><film id="192" fccode="1100" min="12:00" score="30-28"/><film id="197" fccode="1100" min="12:15" score="30-28"/><film id="198" min="12:15" side="0" fccode="1000" playercode="A36553" shottype="1" x="132" y="338" score="32-28"/><film id="199" min="12:15" side="0" fccode="1008" playercode="A49418" score="32-28"/><film id="200" fccode="1100" min="12:30" score="32-28"/><film id="201" min="12:30" side="0" fccode="1007" playercode="A36553" score="32-28"/><film id="202" min="12:30" side="1" fccode="1006" playercode="A03385" score="32-28"/><film id="203" fccode="1100" min="12:45" score="32-28"/><film id="204" min="12:45" side="0" fccode="1011" in="A43627" out="A38968" score="32-28"/><film id="205" min="12:45" side="1" fccode="1007" playercode="A42652" score="32-28"/><film id="206" min="12:45" side="1" fccode="1005" playercode="A42652" score="32-28"/><film id="207" min="12:45" side="0" fccode="1006" playercode="A43412" score="32-28"/><film id="208" min="12:45" side="0" fccode="1004" playercode="A43412" score="32-28"/><film id="209" fccode="1100" min="13:00" score="32-28"/><film id="210" min="13:00" side="1" fccode="1007" playercode="A03385" score="32-28"/><film id="211" min="13:00" side="0" fccode="1006" playercode="A36553" score="32-28"/><film id="212" min="13:00" side="1" fccode="1011" in="8192252" out="A03385" score="32-28"/><film id="213" min="13:00" side="0" fccode="1011" in="A08541" out="A36553" score="32-28"/><film id="214" min="13:00" side="0" fccode="1001" playercode="A43627" shottype="3" x="123" y="207" score="32-28"/><film id="215" min="13:00" side="1" fccode="1002" playercode="A42652" score="32-28"/><film id="216" fccode="1100" min="13:15" score="32-28"/><film id="217" min="13:15" side="1" fccode="1000" playercode="A42652" shottype="3" x="50" y="112" score="32-31"/><film id="218" min="13:15" side="1" fccode="1008" playercode="A47512" score="32-31"/><film id="219" fccode="1100" min="13:30" score="32-31"/><film id="220" fccode="1100" min="13:45" score="32-31"/><film id="221" min="13:45" side="1" fccode="1007" playercode="A47512" score="32-31"/><film id="222" min="13:45" side="0" fccode="1006" playercode="A43627" score="32-31"/><film id="223" fccode="1100" min="14:00" score="32-31"/><film id="228" min="14:00" side="0" fccode="1001" playercode="A43412" shottype="1" x="127" y="323" score="32-31"/><film id="229" min="14:00" side="1" fccode="1002" playercode="A49912" score="32-31"/><film id="230" fccode="1100" min="14:15" score="32-31"/><film id="231" min="14:15" side="0" fccode="1007" playercode="A14098" score="32-31"/><film id="232" min="14:15" side="1" fccode="1006" playercode="A49912" score="32-31"/><film id="233" min="14:15" side="1" fccode="1011" in="A17053" out="A47512" score="32-31"/><film id="234" min="14:15" side="0" fccode="1011" in="A36553" out="A14098" score="32-31"/><film id="235" min="14:15" side="0" fccode="1011" in="A38968" out="A43412" score="32-31"/><film id="236" fccode="1100" min="14:30" score="32-31"/><film id="237" min="14:30" side="1" fccode="1001" playercode="8192252" shottype="3" x="32" y="91" score="32-31"/><film id="238" side="1" min="14:30" fccode="2003" score="32-31"/><film id="239" min="14:30" side="0" fccode="1007" playercode="A08541" score="32-31"/><film id="240" min="14:30" side="1" fccode="1006" playercode="A49912" score="32-31"/><film id="241" min="14:30" side="0" fccode="1011" in="A43412" out="A08541" score="32-31"/><film id="242" min="14:30" side="1" fccode="1005" playercode="8192252" score="32-31"/><film id="243" min="14:30" side="0" fccode="1004" playercode="A43627" score="32-31"/><film id="244" fccode="1100" min="14:45" score="32-31"/><film id="245" min="14:45" side="1" fccode="1007" playercode="8192252" score="32-31"/><film id="246" min="14:45" side="0" fccode="1006" playercode="A43627" score="32-31"/><film id="247" min="14:45" side="0" fccode="1001" playercode="A36553" shottype="1" x="155" y="318" score="32-31"/><film id="248" min="14:45" side="1" fccode="1002" playercode="A42652" score="32-31"/><film id="249" fccode="1100" min="15:00" score="32-31"/><film id="250" fccode="1100" min="15:15" score="32-31"/><film id="251" min="15:15" side="0" fccode="1007" playercode="A36553" score="32-31"/><film id="252" min="15:15" side="1" fccode="1006" playercode="A49912" score="32-31"/><film id="263" min="15:15" side="1" fccode="1001" playercode="A49912" shottype="4" x="0" y="0" score="32-31"/><film id="264" min="15:15" side="1" fccode="1001" playercode="A49912" shottype="4" x="0" y="0" score="32-31"/><film id="265" min="15:15" side="0" fccode="1002" playercode="A36553" score="32-31"/><film id="266" fccode="1100" min="15:30" score="32-31"/><film id="267" min="15:30" side="0" fccode="1005" playercode="A43412" score="32-31"/><film id="268" fccode="1100" min="15:45" score="32-31"/><film id="269" min="15:45" side="1" fccode="1001" playercode="A42652" shottype="2" x="96" y="83" score="32-31"/><film id="270" min="15:45" side="1" fccode="1003" playercode="A49912" score="32-31"/><film id="271" min="15:45" side="1" fccode="1006" playercode="A49912" score="32-31"/><film id="272" min="15:45" side="0" fccode="1007" playercode="A43412" score="32-31"/><film id="273" min="15:45" side="1" fccode="1000" playercode="A49912" shottype="4" x="0" y="0" score="32-32"/><film id="274" min="15:45" side="1" fccode="1001" playercode="A49912" shottype="4" x="0" y="0" score="32-32"/><film id="275" min="15:45" side="0" fccode="1002" playercode="A36553" score="32-32"/><film id="276" fccode="1100" min="16:00" score="32-32"/><film id="281" min="16:00" side="1" fccode="1007" playercode="A17053" score="32-32"/><film id="282" min="16:00" side="0" fccode="1006" playercode="A43412" score="32-32"/><film id="283" min="16:00" side="0" fccode="1001" playercode="A43412" shottype="4" x="0" y="0" score="32-32"/><film id="284" min="16:00" side="0" fccode="1000" playercode="A43412" shottype="4" x="0" y="0" score="33-32"/><film id="285" side="0" min="16:00" fccode="2011" score="33-32"/><film id="286" min="16:00" side="1" fccode="1011" in="A32730" out="A49912" score="33-32"/><film id="287" fccode="1100" min="16:15" score="33-32"/><film id="288" min="16:15" side="1" fccode="1000" playercode="A46327" shottype="3" x="83" y="127" score="33-35"/><film id="289" fccode="1100" min="16:30" score="33-35"/><film id="290" min="16:30" side="0" fccode="1001" playercode="A43627" shottype="1" x="134" y="327" score="33-35"/><film id="291" min="16:30" side="0" fccode="1003" playercode="A43627" score="33-35"/><film id="292" min="16:30" side="0" fccode="1001" playercode="A43627" shottype="1" x="129" y="326" score="33-35"/><film id="293" min="16:30" side="1" fccode="1002" playercode="A17053" score="33-35"/><film id="294" min="16:30" side="1" fccode="1005" playercode="A17053" score="33-35"/><film id="295" min="16:30" side="0" fccode="1004" playercode="A43412" score="33-35"/><film id="296" fccode="1100" min="16:45" score="33-35"/><film id="297" fccode="1100" min="17:00" score="33-35"/><film id="298" min="17:00" side="0" fccode="1001" playercode="A38968" shottype="2" x="64" y="287" score="33-35"/><film id="299" side="1" min="17:00" fccode="2002" score="33-35"/><film id="300" min="17:00" side="0" fccode="1011" in="A08541" out="A36553" score="33-35"/><film id="301" min="17:00" side="1" fccode="1007" playercode="A46327" score="33-35"/><film id="302" min="17:00" side="1" fccode="1005" playercode="A46327" score="33-35"/><film id="303" min="17:00" side="0" fccode="1004" playercode="A43627" score="33-35"/><film id="304" min="17:00" side="0" fccode="1006" playercode="A43627" score="33-35"/><film id="305" fccode="1100" min="17:15" score="33-35"/><film id="306" min="17:15" side="1" fccode="1011" in="A47512" out="8192252" score="33-35"/><film id="307" fccode="1100" min="17:30" score="33-35"/><film id="308" min="17:30" side="0" fccode="1001" playercode="A49418" shottype="3" x="189" y="246" score="33-35"/><film id="309" min="17:30" side="1" fccode="1002" playercode="A46327" score="33-35"/><film id="310" fccode="1100" min="17:45" score="33-35"/><film id="311" min="17:45" side="1" fccode="1005" playercode="A17053" score="33-35"/><film id="312" min="17:45" side="0" fccode="1004" playercode="A08541" score="33-35"/><film id="313" min="17:45" side="0" fccode="1006" playercode="A43627" score="33-35"/><film id="314" min="17:45" side="1" fccode="1007" playercode="A32730" score="33-35"/><film id="315" min="17:45" side="1" fccode="1011" in="A03385" out="A17053" score="33-35"/><film id="316" min="17:45" side="0" fccode="1001" playercode="A43627" shottype="4" x="0" y="0" score="33-35"/><film id="317" min="17:45" side="0" fccode="1000" playercode="A43627" shottype="4" x="0" y="0" score="34-35"/><film id="318" min="17:45" side="0" fccode="1008" playercode="A43412" score="34-35"/><film id="319" fccode="1100" min="18:00" score="34-35"/><film id="324" min="18:00" side="1" fccode="1001" playercode="A47512" shottype="2" x="111" y="99" score="34-35"/><film id="325" min="18:00" side="0" fccode="1002" playercode="A43627" score="34-35"/><film id="326" fccode="1100" min="18:15" score="34-35"/><film id="327" fccode="1100" min="18:30" score="34-35"/><film id="328" min="18:30" side="0" fccode="1000" playercode="A43627" shottype="3" x="226" y="312" score="37-35"/><film id="329" min="18:30" side="0" fccode="1008" playercode="A43412" score="37-35"/><film id="330" side="1" min="18:30" fccode="2011" score="37-35"/><film id="331" fccode="1100" min="18:45" score="37-35"/><film id="332" min="18:45" side="0" fccode="1007" playercode="A08541" score="37-35"/><film id="333" min="18:45" side="1" fccode="1006" playercode="A46327" score="37-35"/><film id="334" min="18:45" side="1" fccode="1011" in="A49912" out="A42652" score="37-35"/><film id="335" min="18:45" side="1" fccode="1011" in="A42652" out="A03385" score="37-35"/><film id="336" min="18:45" side="1" fccode="1011" in="8192252" out="A32730" score="37-35"/><film id="337" min="18:45" side="1" fccode="1000" playercode="A46327" shottype="4" x="0" y="0" score="37-36"/><film id="338" min="18:45" side="1" fccode="1000" playercode="A46327" shottype="4" x="0" y="0" score="37-37"/><film id="339" fccode="1100" min="19:00" score="37-37"/><film id="340" min="19:00" side="0" fccode="1001" playercode="A43627" shottype="2" x="75" y="328" score="37-37"/><film id="341" min="19:00" side="1" fccode="1002" playercode="A42652" score="37-37"/><film id="342" fccode="1100" min="19:15" score="37-37"/><film id="343" min="19:15" side="1" fccode="1001" playercode="A42652" shottype="1" x="110" y="31" score="37-37"/><film id="344" min="19:15" side="0" fccode="1002" playercode="A38968" score="37-37"/><film id="345" min="19:15" side="0" fccode="1000" playercode="A43412" shottype="1" x="132" y="333" score="39-37"/><film id="346" min="19:15" side="0" fccode="1008" playercode="A38968" score="39-37"/><film id="347" fccode="1100" min="19:30" score="39-37"/><film id="348" fccode="1100" min="19:45" score="39-37"/><film id="349" min="19:45" side="0" fccode="1007" playercode="A43627" score="39-37"/><film id="350" min="19:45" side="1" fccode="1006" playercode="A49912" score="39-37"/><film id="351" side="0" min="19:45" fccode="2011" score="39-37"/><film id="352" min="19:45" side="1" fccode="1000" playercode="A49912" shottype="4" x="0" y="0" score="39-38"/><film id="353" min="19:45" side="1" fccode="1008" playercode="A46327" score="39-38"/><film id="354" min="19:45" side="1" fccode="1000" playercode="A49912" shottype="4" x="0" y="0" score="39-39"/><film id="355" min="19:45" side="0" fccode="1011" in="A14098" out="A43412" score="39-39"/><film id="356" min="19:45" side="0" fccode="1001" playercode="A43627" shottype="1" x="131" y="323" score="39-39"/><film id="357" min="19:45" side="0" fccode="1010" playercode="A43627" score="39-39"/><film id="358" min="19:45" side="1" fccode="1009" playercode="A49912" score="39-39"/><film id="359" side="0" min="19:45" fccode="2003" score="39-39"/><film id="360" fccode="1100" min="20:00" score="39-39"/><film id="365" fccode="1101" period="4" min="20:00" score="39-39"/><film id="371" min="20:00" side="0" fccode="1011" in="A43412" out="A08541" score="39-39"/><film id="372" min="20:00" side="0" fccode="1011" in="A36553" out="A49418" score="39-39"/><film id="373" min="20:00" side="1" fccode="1011" in="A32730" out="A49912" score="39-39"/><film id="374" min="20:00" side="1" fccode="1011" in="A17053" out="8192252" score="39-39"/><film id="375" fccode="1100" min="20:15" score="39-39"/><film id="376" min="20:15" side="1" fccode="1000" playercode="A46327" shottype="3" x="225" y="48" score="39-42"/><film id="377" min="20:15" side="1" fccode="1008" playercode="A42652" score="39-42"/><film id="378" fccode="1100" min="20:30" score="39-42"/><film id="379" fccode="1100" min="20:45" score="39-42"/><film id="380" min="20:45" side="0" fccode="1005" playercode="A36553" score="39-42"/><film id="381" min="20:45" side="1" fccode="1004" playercode="A17053" score="39-42"/><film id="382" min="20:45" side="1" fccode="1001" playercode="A47512" shottype="3" x="143" y="130" score="39-42"/><film id="383" min="20:45" side="1" fccode="1003" playercode="A17053" score="39-42"/><film id="384" min="20:45" side="1" fccode="1005" playercode="A17053" score="39-42"/><film id="385" min="20:45" side="0" fccode="1004" playercode="A43412" score="39-42"/><film id="386" fccode="1100" min="21:00" score="39-42"/><film id="387" min="21:00" side="0" fccode="1005" playercode="A43627" score="39-42"/><film id="388" min="21:00" side="1" fccode="1004" playercode="A17053" score="39-42"/><film id="389" min="21:00" side="1" fccode="1000" playercode="A17053" shottype="2" x="139" y="85" score="39-44"/><film id="390" fccode="1100" min="21:15" score="39-44"/><film id="391" fccode="1100" min="21:30" score="39-44"/><film id="392" min="21:30" side="0" fccode="1005" playercode="A14098" score="39-44"/><film id="393" min="21:30" side="1" fccode="1004" playercode="A46327" score="39-44"/><film id="394" min="21:30" side="1" fccode="1000" playercode="A46327" shottype="1" x="131" y="20" score="39-46"/><film id="395" fccode="1100" min="21:45" score="39-46"/><film id="396" min="21:45" side="0" fccode="1007" playercode="A43627" score="39-46"/><film id="397" min="21:45" side="0" fccode="1005" playercode="A43627" score="39-46"/><film id="398" min="21:45" side="1" fccode="1006" playercode="A17053" score="39-46"/><film id="399" min="21:45" side="1" fccode="1004" playercode="A17053" score="39-46"/><film id="400" side="0" min="21:45" fccode="2011" score="39-46"/><film id="401" fccode="1100" min="22:00" score="39-46"/><film id="406" min="22:00" side="1" fccode="1005" playercode="A47512" score="39-46"/><film id="407" min="22:00" side="0" fccode="1004" playercode="A38968" score="39-46"/><film id="408" fccode="1100" min="22:15" score="39-46"/><film id="409" min="22:15" side="0" fccode="1005" playercode="A43627" score="39-46"/><film id="410" min="22:15" side="1" fccode="1004" playercode="A47512" score="39-46"/><film id="411" min="22:15" side="0" fccode="1007" playercode="A14098" score="39-46"/><film id="412" min="22:15" side="1" fccode="1006" playercode="A47512" score="39-46"/><film id="413" min="22:15" side="0" fccode="1011" in="A49418" out="A43627" score="39-46"/><film id="414" fccode="1100" min="22:30" score="39-46"/><film id="415" fccode="1100" min="22:45" score="39-46"/><film id="416" min="22:45" side="1" fccode="1001" playercode="A17053" shottype="2" x="189" y="31" score="39-46"/><film id="417" min="22:45" side="0" fccode="1002" playercode="A38968" score="39-46"/><film id="418" fccode="1100" min="23:00" score="39-46"/><film id="419" min="23:00" side="0" fccode="1005" playercode="A38968" score="39-46"/><film id="420" fccode="1100" min="23:15" score="39-46"/><film id="421" min="23:15" side="0" fccode="1007" playercode="A43412" score="39-46"/><film id="422" min="23:15" side="1" fccode="1006" playercode="A42652" score="39-46"/><film id="423" fccode="1100" min="23:30" score="39-46"/><film id="424" min="23:30" side="1" fccode="1001" playercode="A47512" shottype="2" x="26" y="20" score="39-46"/><film id="425" min="23:30" side="0" fccode="1002" playercode="A38968" score="39-46"/><film id="426" min="23:30" side="0" fccode="1005" playercode="A38968" score="39-46"/><film id="427" min="23:30" side="1" fccode="1004" playercode="A42652" score="39-46"/><film id="428" min="23:30" side="0" fccode="1007" playercode="A49418" score="39-46"/><film id="429" min="23:30" side="1" fccode="1006" playercode="A42652" score="39-46"/><film id="430" min="23:30" side="0" fccode="1011" in="A43627" out="A43412" score="39-46"/><film id="431" fccode="1100" min="23:45" score="39-46"/><film id="432" min="23:45" side="0" fccode="1007" playercode="A14098" score="39-46"/><film id="433" min="23:45" side="1" fccode="1006" playercode="A17053" score="39-46"/><film id="434" min="23:45" side="0" fccode="1011" in="A43412" out="A14098" score="39-46"/><film id="435" min="23:45" side="1" fccode="1000" playercode="A17053" shottype="4" x="0" y="0" score="39-47"/><film id="436" min="23:45" side="1" fccode="1000" playercode="A17053" shottype="4" x="0" y="0" score="39-48"/><film id="437" fccode="1100" min="24:00" score="39-48"/><film id="442" min="24:00" side="0" fccode="1005" playercode="A43412" score="39-48"/><film id="443" min="24:00" side="1" fccode="1000" playercode="A42652" shottype="3" x="229" y="29" score="39-51"/><film id="444" min="24:00" side="1" fccode="1008" playercode="A46327" score="39-51"/><film id="445" fccode="1100" min="24:15" score="39-51"/><film id="446" fccode="1100" min="24:30" score="39-51"/><film id="447" min="24:30" side="1" fccode="1007" playercode="A46327" score="39-51"/><film id="448" min="24:30" side="0" fccode="1006" playercode="A49418" score="39-51"/><film id="449" side="0" min="24:30" fccode="2011" score="39-51"/><film id="450" min="24:30" side="0" fccode="1001" playercode="A43412" shottype="2" x="126" y="260" score="39-51"/><film id="451" min="24:30" side="1" fccode="1002" playercode="A17053" score="39-51"/><film id="452" fccode="1100" min="24:45" score="39-51"/><film id="453" fccode="1100" min="25:00" score="39-51"/><film id="454" min="25:00" side="1" fccode="1001" playercode="A32730" shottype="1" x="116" y="55" score="39-51"/><film id="455" min="25:00" side="1" fccode="1010" playercode="A32730" score="39-51"/><film id="456" min="25:00" side="0" fccode="1009" playercode="A43412" score="39-51"/><film id="457" side="1" min="25:00" fccode="2003" score="39-51"/><film id="458" min="25:00" side="1" fccode="1001" playercode="A42652" shottype="5" x="119" y="21" score="39-51"/><film id="459" min="25:00" side="1" fccode="1003" playercode="A32730" score="39-51"/><film id="460" min="25:00" side="1" fccode="1006" playercode="A32730" score="39-51"/><film id="461" min="25:00" side="0" fccode="1007" playercode="A43627" score="39-51"/><film id="462" min="25:00" side="1" fccode="1000" playercode="A32730" shottype="4" x="0" y="0" score="39-52"/><film id="463" min="25:00" side="1" fccode="1001" playercode="A32730" shottype="4" x="0" y="0" score="39-52"/><film id="464" min="25:00" side="0" fccode="1002" playercode="A43412" score="39-52"/><film id="465" fccode="1100" min="25:15" score="39-52"/><film id="466" min="25:15" side="1" fccode="1007" playercode="A17053" score="39-52"/><film id="467" min="25:15" side="0" fccode="1006" playercode="A49418" score="39-52"/><film id="468" fccode="1100" min="25:30" score="39-52"/><film id="469" min="25:30" side="0" fccode="1000" playercode="A36553" shottype="1" x="128" y="332" score="41-52"/><film id="470" min="25:30" side="0" fccode="1008" playercode="A43412" score="41-52"/><film id="471" min="25:30" side="1" fccode="1007" playercode="A32730" score="41-52"/><film id="472" min="25:30" side="0" fccode="1006" playercode="A36553" score="41-52"/><film id="473" min="25:30" side="1" fccode="1011" in="A49912" out="A32730" score="41-52"/><film id="474" min="25:30" side="0" fccode="1000" playercode="A36553" shottype="4" x="0" y="0" score="42-52"/><film id="475" fccode="1100" min="25:45" score="42-52"/><film id="476" fccode="1100" min="26:00" score="42-52"/><film id="481" min="26:00" side="1" fccode="1000" playercode="A17053" shottype="1" x="121" y="35" score="42-54"/><film id="482" min="26:00" side="1" fccode="1008" playercode="A47512" score="42-54"/><film id="483" fccode="1100" min="26:15" score="42-54"/><film id="484" min="26:15" side="0" fccode="1000" playercode="A43627" shottype="1" x="138" y="334" score="44-54"/><film id="485" min="26:15" side="0" fccode="1008" playercode="A49418" score="44-54"/><film id="486" fccode="1100" min="26:30" score="44-54"/><film id="487" min="26:30" side="1" fccode="1001" playercode="A49912" shottype="1" x="125" y="51" score="44-54"/><film id="488" min="26:30" side="1" fccode="1010" playercode="A49912" score="44-54"/><film id="489" min="26:30" side="0" fccode="1009" playercode="A38968" score="44-54"/><film id="490" min="26:30" side="0" fccode="1002" playercode="A43412" score="44-54"/><film id="491" fccode="1100" min="26:45" score="44-54"/><film id="492" fccode="1100" min="27:00" score="44-54"/><film id="493" min="27:00" side="0" fccode="1001" playercode="A38968" shottype="3" x="38" y="253" score="44-54"/><film id="494" min="27:00" side="0" fccode="1003" playercode="A43627" score="44-54"/><film id="495" min="27:00" side="0" fccode="1006" playercode="A43627" score="44-54"/><film id="496" min="27:00" side="1" fccode="1007" playercode="A49912" score="44-54"/><film id="497" min="27:00" side="0" fccode="1011" in="A08541" out="A38968" score="44-54"/><film id="498" min="27:00" side="1" fccode="1011" in="A03385" out="A17053" score="44-54"/><film id="499" min="27:00" side="0" fccode="1000" playercode="A43627" shottype="2" x="119" y="253" score="46-54"/><film id="500" fccode="1100" min="27:15" score="46-54"/><film id="501" fccode="1100" min="27:30" score="46-54"/><film id="502" min="27:30" side="0" fccode="1007" playercode="A43412" score="46-54"/><film id="503" min="27:30" side="1" fccode="1006" playercode="A49912" score="46-54"/><film id="504" min="27:30" side="1" fccode="1001" playercode="A49912" shottype="4" x="0" y="0" score="46-54"/><film id="505" min="27:30" side="1" fccode="1000" playercode="A49912" shottype="4" x="0" y="0" score="46-55"/><film id="506" min="27:30" side="1" fccode="1008" playercode="A42652" score="46-55"/><film id="507" min="27:30" side="0" fccode="1011" in="A35678" out="A43412" score="46-55"/><film id="508" min="27:30" side="0" fccode="1001" playercode="A36553" shottype="1" x="104" y="327" score="46-55"/><film id="509" min="27:30" side="1" fccode="1002" playercode="A03385" score="46-55"/><film id="510" fccode="1100" min="27:45" score="46-55"/><film id="511" min="27:45" side="1" fccode="1001" playercode="A49912" shottype="5" x="118" y="23" score="46-55"/><film id="512" min="27:45" side="0" fccode="1002" playercode="A43627" score="46-55"/><film id="513" fccode="1100" min="28:00" score="46-55"/><film id="518" min="28:00" side="0" fccode="1005" playercode="A36553" score="46-55"/><film id="519" fccode="1100" min="28:15" score="46-55"/><film id="520" min="28:15" side="1" fccode="1001" playercode="A03385" shottype="2" x="156" y="90" score="46-55"/><film id="521" min="28:15" side="1" fccode="1003" playercode="A47512" score="46-55"/><film id="522" min="28:15" side="1" fccode="1000" playercode="A47512" shottype="1" x="126" y="24" score="46-57"/><film id="523" fccode="1100" min="28:30" score="46-57"/><film id="524" fccode="1100" min="28:45" score="46-57"/><film id="525" min="28:45" side="0" fccode="1001" playercode="A35678" shottype="3" x="27" y="274" score="46-57"/><film id="526" min="28:45" side="1" fccode="1002" playercode="A42652" score="46-57"/><film id="527" fccode="1100" min="29:00" score="46-57"/><film id="528" min="29:00" side="1" fccode="1001" playercode="A42652" shottype="1" x="137" y="21" score="46-57"/><film id="529" min="29:00" side="1" fccode="1003" playercode="A42652" score="46-57"/><film id="530" min="29:00" side="0" fccode="1007" playercode="A08541" score="46-57"/><film id="531" min="29:00" side="1" fccode="1006" playercode="A42652" score="46-57"/><film id="532" min="29:00" side="1" fccode="1011" in="8192252" out="A47512" score="46-57"/><film id="533" min="29:00" side="0" fccode="1011" in="A38968" out="A08541" score="46-57"/><film id="534" min="29:00" side="0" fccode="1011" in="A14098" out="A49418" score="46-57"/><film id="535" min="29:00" side="1" fccode="1001" playercode="A42652" shottype="4" x="0" y="0" score="46-57"/><film id="536" min="29:00" side="1" fccode="1000" playercode="A42652" shottype="4" x="0" y="0" score="46-58"/><film id="537" min="29:00" side="1" fccode="1011" in="A32730" out="A42652" score="46-58"/><film id="538" fccode="1100" min="29:15" score="46-58"/><film id="539" min="29:15" side="0" fccode="1001" playercode="A35678" shottype="1" x="120" y="313" score="46-58"/><film id="540" side="0" min="29:15" fccode="2003" score="46-58"/><film id="541" min="29:15" side="0" fccode="1011" in="A55148" out="A35678" score="46-58"/><film id="542" fccode="1100" min="29:30" score="46-58"/><film id="543" min="29:30" side="1" fccode="1007" playercode="A03385" score="46-58"/><film id="544" min="29:30" side="0" fccode="1006" playercode="A43627" score="46-58"/><film id="545" min="29:30" side="0" fccode="1011" in="A35678" out="A14098" score="46-58"/><film id="546" min="29:30" side="0" fccode="1001" playercode="A43627" shottype="4" x="0" y="0" score="46-58"/><film id="547" min="29:30" side="0" fccode="1000" playercode="A43627" shottype="4" x="0" y="0" score="47-58"/><film id="548" fccode="1100" min="29:45" score="47-58"/><film id="549" min="29:45" side="1" fccode="1000" playercode="A32730" shottype="1" x="103" y="25" score="47-60"/><film id="550" min="29:45" side="1" fccode="1008" playercode="8192252" score="47-60"/><film id="551" min="29:45" side="0" fccode="1001" playercode="A36553" shottype="1" x="135" y="331" score="47-60"/><film id="552" min="29:45" side="1" fccode="1002" playercode="A49912" score="47-60"/><film id="553" min="29:45" side="1" fccode="1000" playercode="A49912" shottype="5" x="118" y="23" score="47-62"/><film id="554" min="29:45" side="1" fccode="1008" playercode="A03385" score="47-62"/><film id="555" fccode="1100" min="30:00" score="47-62"/><film id="560" fccode="1101" period="4" min="30:00" score="47-62"/><film id="565" min="30:00" side="0" fccode="1011" in="A43412" out="A55148" score="47-62"/><film id="566" min="30:00" side="0" fccode="1011" in="A14098" out="A35678" score="47-62"/><film id="567" min="30:00" side="1" fccode="1011" in="A47512" out="8192252" score="47-62"/><film id="568" fccode="1100" min="30:15" score="47-62"/><film id="569" min="30:15" side="1" fccode="1007" playercode="A49912" score="47-62"/><film id="570" min="30:15" side="0" fccode="1006" playercode="A36553" score="47-62"/><film id="571" min="30:15" side="0" fccode="1000" playercode="A36553" shottype="4" x="0" y="0" score="48-62"/><film id="572" min="30:15" side="0" fccode="1000" playercode="A36553" shottype="4" x="0" y="0" score="49-62"/><film id="573" min="30:15" side="0" fccode="1008" playercode="A14098" score="49-62"/><film id="574" fccode="1100" min="30:30" score="49-62"/><film id="575" min="30:30" side="1" fccode="1001" playercode="A47512" shottype="2" x="53" y="39" score="49-62"/><film id="576" min="30:30" side="0" fccode="1002" playercode="A36553" score="49-62"/><film id="577" min="30:30" side="1" fccode="1007" playercode="A46327" score="49-62"/><film id="578" min="30:30" side="0" fccode="1006" playercode="A43627" score="49-62"/><film id="579" min="30:30" side="0" fccode="1000" playercode="A43627" shottype="4" x="0" y="0" score="50-62"/><film id="580" min="30:30" side="0" fccode="1001" playercode="A43627" shottype="4" x="0" y="0" score="50-62"/><film id="581" fccode="1100" min="30:45" score="50-62"/><film id="582" min="30:45" side="0" fccode="1000" playercode="A36553" shottype="2" x="171" y="333" score="52-62"/><film id="583" fccode="1100" min="31:00" score="52-62"/><film id="584" min="31:00" side="1" fccode="1001" playercode="A49912" shottype="1" x="117" y="41" score="52-62"/><film id="585" side="1" min="31:00" fccode="2003" score="52-62"/><film id="586" min="31:00" side="1" fccode="1011" in="A42652" out="A49912" score="52-62"/><film id="587" fccode="1100" min="31:15" score="52-62"/><film id="588" min="31:15" side="1" fccode="1000" playercode="A42652" shottype="3" x="118" y="129" score="52-65"/><film id="589" min="31:15" side="1" fccode="1008" playercode="A03385" score="52-65"/><film id="590" fccode="1100" min="31:30" score="52-65"/><film id="591" fccode="1100" min="31:45" score="52-65"/><film id="592" min="31:45" side="0" fccode="1001" playercode="A43412" shottype="3" x="11" y="326" score="52-65"/><film id="593" min="31:45" side="1" fccode="1002" playercode="A03385" score="52-65"/><film id="594" fccode="1100" min="32:00" score="52-65"/><film id="599" min="32:00" side="1" fccode="1000" playercode="A42652" shottype="5" x="118" y="22" score="52-67"/><film id="600" min="32:00" side="1" fccode="1008" playercode="A32730" score="52-67"/><film id="601" fccode="1100" min="32:15" score="52-67"/><film id="602" min="32:15" side="0" fccode="1000" playercode="A38968" shottype="2" x="90" y="265" score="54-67"/><film id="603" fccode="1100" min="32:30" score="54-67"/><film id="604" min="32:30" side="1" fccode="1001" playercode="A46327" shottype="3" x="222" y="58" score="54-67"/><film id="605" min="32:30" side="0" fccode="1002" playercode="A43412" score="54-67"/><film id="606" fccode="1100" min="32:45" score="54-67"/><film id="607" min="32:45" side="1" fccode="1007" playercode="A32730" score="54-67"/><film id="608" min="32:45" side="0" fccode="1006" playercode="A43627" score="54-67"/><film id="609" min="32:45" side="0" fccode="1000" playercode="A43627" shottype="4" x="0" y="0" score="55-67"/><film id="610" min="32:45" side="0" fccode="1000" playercode="A43627" shottype="4" x="0" y="0" score="56-67"/><film id="611" min="32:45" side="1" fccode="1011" in="A49912" out="A32730" score="56-67"/><film id="612" fccode="1100" min="33:00" score="56-67"/><film id="613" min="33:00" side="0" fccode="1007" playercode="A43412" score="56-67"/><film id="614" min="33:00" side="1" fccode="1006" playercode="A49912" score="56-67"/><film id="615" fccode="1100" min="33:15" score="56-67"/><film id="616" min="33:15" side="1" fccode="1011" in="A17053" out="A46327" score="56-67"/><film id="617" min="33:15" side="0" fccode="1011" in="A49418" out="A43412" score="56-67"/><film id="618" min="33:15" side="1" fccode="1001" playercode="A49912" shottype="4" x="0" y="0" score="56-67"/><film id="619" min="33:15" side="1" fccode="1000" playercode="A49912" shottype="4" x="0" y="0" score="56-68"/><film id="620" min="33:15" side="1" fccode="1008" playercode="A42652" score="56-68"/><film id="621" fccode="1100" min="33:30" score="56-68"/><film id="622" min="33:30" side="0" fccode="1001" playercode="A49418" shottype="3" x="203" y="265" score="56-68"/><film id="623" min="33:30" side="1" fccode="1002" playercode="A03385" score="56-68"/><film id="624" min="33:30" side="1" fccode="1000" playercode="A47512" shottype="2" x="181" y="74" score="56-70"/><film id="625" min="33:30" side="1" fccode="1008" playercode="A42652" score="56-70"/><film id="626" fccode="1100" min="33:45" score="56-70"/><film id="627" fccode="1100" min="34:00" score="56-70"/><film id="632" min="34:00" side="0" fccode="1001" playercode="A36553" shottype="1" x="117" y="319" score="56-70"/><film id="633" min="34:00" side="0" fccode="1010" playercode="A36553" score="56-70"/><film id="634" min="34:00" side="1" fccode="1009" playercode="A42652" score="56-70"/><film id="635" min="34:00" side="1" fccode="1002" playercode="A47512" score="56-70"/><film id="636" min="34:00" side="1" fccode="1005" playercode="A47512" score="56-70"/><film id="637" min="34:00" side="0" fccode="1004" playercode="A36553" score="56-70"/><film id="638" min="34:00" side="0" fccode="1006" playercode="A38968" score="56-70"/><film id="639" min="34:00" side="1" fccode="1007" playercode="A42652" score="56-70"/><film id="640" min="34:00" side="0" fccode="1000" playercode="A38968" shottype="4" x="0" y="0" score="57-70"/><film id="641" fccode="1100" min="34:15" score="57-70"/><film id="642" min="34:15" side="0" fccode="1001" playercode="A38968" shottype="4" x="0" y="0" score="57-70"/><film id="643" min="34:15" side="1" fccode="1002" playercode="A42652" score="57-70"/><film id="644" min="34:15" side="1" fccode="1005" playercode="A42652" score="57-70"/><film id="645" min="34:15" side="0" fccode="1004" playercode="A38968" score="57-70"/><film id="646" fccode="1100" min="34:30" score="57-70"/><film id="647" min="34:30" side="0" fccode="1001" playercode="A43627" shottype="3" x="197" y="254" score="57-70"/><film id="648" min="34:30" side="1" fccode="1002" playercode="A03385" score="57-70"/><film id="649" fccode="1100" min="34:45" score="57-70"/><film id="650" fccode="1100" min="35:00" score="57-70"/><film id="651" min="35:00" side="1" fccode="1001" playercode="A42652" shottype="2" x="153" y="68" score="57-70"/><film id="652" min="35:00" side="0" fccode="1002" playercode="A38968" score="57-70"/><film id="653" fccode="1100" min="35:15" score="57-70"/><film id="654" min="35:15" side="0" fccode="1011" in="A08541" out="A38968" score="57-70"/><film id="655" fccode="1100" min="35:30" score="57-70"/><film id="656" min="35:30" side="0" fccode="1001" playercode="A14098" shottype="3" x="191" y="245" score="57-70"/><film id="657" min="35:30" side="1" fccode="1002" playercode="A42652" score="57-70"/><film id="658" min="35:30" side="0" fccode="1007" playercode="A08541" score="57-70"/><film id="659" min="35:30" side="1" fccode="1006" playercode="A42652" score="57-70"/><film id="660" fccode="1100" min="35:45" score="57-70"/><film id="661" min="35:45" side="1" fccode="1005" playercode="A49912" score="57-70"/><film id="662" min="35:45" side="0" fccode="1004" playercode="A43627" score="57-70"/><film id="663" min="35:45" side="0" fccode="1001" playercode="A43627" shottype="1" x="103" y="335" score="57-70"/><film id="664" min="35:45" side="1" fccode="1002" playercode="A49912" score="57-70"/><film id="665" fccode="1100" min="36:00" score="57-70"/><film id="670" min="36:00" side="1" fccode="1000" playercode="A42652" shottype="1" x="114" y="41" score="57-72"/><film id="671" fccode="1100" min="36:15" score="57-72"/><film id="672" min="36:15" side="0" fccode="1000" playercode="A36553" shottype="1" x="133" y="329" score="59-72"/><film id="673" min="36:15" side="0" fccode="1008" playercode="A49418" score="59-72"/><film id="674" min="36:15" side="0" fccode="1006" playercode="A36553" score="59-72"/><film id="675" min="36:15" side="1" fccode="1007" playercode="A49912" score="59-72"/><film id="676" min="36:15" side="1" fccode="1011" in="A46327" out="A03385" score="59-72"/><film id="677" min="36:15" side="0" fccode="1000" playercode="A36553" shottype="4" x="0" y="0" score="60-72"/><film id="678" fccode="1100" min="36:30" score="60-72"/><film id="679" min="36:30" side="1" fccode="1007" playercode="A49912" score="60-72"/><film id="680" min="36:30" side="0" fccode="1006" playercode="A14098" score="60-72"/><film id="681" min="36:30" side="1" fccode="1005" playercode="A49912" score="60-72"/><film id="682" min="36:30" side="0" fccode="1004" playercode="A14098" score="60-72"/><film id="683" min="36:30" side="1" fccode="1011" in="A32730" out="A49912" score="60-72"/><film id="684" fccode="1100" min="36:45" score="60-72"/><film id="685" min="36:45" side="1" fccode="1007" playercode="A42652" score="60-72"/><film id="686" min="36:45" side="0" fccode="1006" playercode="A36553" score="60-72"/><film id="687" min="36:45" side="1" fccode="1011" in="A03385" out="A17053" score="60-72"/><film id="688" min="36:45" side="0" fccode="1000" playercode="A36553" shottype="4" x="0" y="0" score="61-72"/><film id="689" min="36:45" side="0" fccode="1008" playercode="A49418" score="61-72"/><film id="690" min="36:45" side="0" fccode="1001" playercode="A36553" shottype="4" x="0" y="0" score="61-72"/><film id="691" min="36:45" side="1" fccode="1002" playercode="A42652" score="61-72"/><film id="692" fccode="1100" min="37:00" score="61-72"/><film id="693" min="37:00" side="1" fccode="1005" playercode="A32730" score="61-72"/><film id="694" min="37:00" side="0" fccode="1000" playercode="A49418" shottype="3" x="123" y="224" score="64-72"/><film id="695" side="1" min="37:00" fccode="2011" score="64-72"/><film id="696" fccode="1100" min="37:15" score="64-72"/><film id="697" min="37:15" side="1" fccode="1000" playercode="A47512" shottype="3" x="198" y="100" score="64-75"/><film id="698" min="37:15" side="1" fccode="1008" playercode="A42652" score="64-75"/><film id="699" fccode="1100" min="37:30" score="64-75"/><film id="700" fccode="1100" min="37:45" score="64-75"/><film id="701" min="37:45" side="0" fccode="1001" playercode="A36553" shottype="1" x="133" y="321" score="64-75"/><film id="702" min="37:45" side="0" fccode="1010" playercode="A36553" score="64-75"/><film id="703" min="37:45" side="1" fccode="1009" playercode="A32730" score="64-75"/><film id="704" min="37:45" side="1" fccode="1002" playercode="A47512" score="64-75"/><film id="705" min="37:45" side="0" fccode="1007" playercode="A49418" score="64-75"/><film id="706" min="37:45" side="1" fccode="1006" playercode="A47512" score="64-75"/><film id="707" fccode="1100" min="38:00" score="64-75"/><film id="712" min="38:00" side="1" fccode="1001" playercode="A42652" shottype="2" x="170" y="22" score="64-75"/><film id="713" min="38:00" side="0" fccode="1002" playercode="A08541" score="64-75"/><film id="714" fccode="1100" min="38:15" score="64-75"/><film id="715" min="38:15" side="0" fccode="1001" playercode="A08541" shottype="3" x="111" y="224" score="64-75"/><film id="716" min="38:15" side="1" fccode="1002" playercode="A42652" score="64-75"/><film id="717" fccode="1100" min="38:30" score="64-75"/><film id="718" fccode="1100" min="38:45" score="64-75"/><film id="719" min="38:45" side="1" fccode="1007" playercode="A32730" score="64-75"/><film id="720" min="38:45" side="1" fccode="1005" playercode="A32730" score="64-75"/><film id="721" min="38:45" side="0" fccode="1006" playercode="A43627" score="64-75"/><film id="722" min="38:45" side="0" fccode="1004" playercode="A43627" score="64-75"/><film id="723" side="0" min="38:45" fccode="2011" score="64-75"/><film id="724" min="38:45" side="1" fccode="1011" in="A17053" out="A46327" score="64-75"/><film id="725" min="38:45" side="1" fccode="1011" in="A46327" out="A32730" score="64-75"/><film id="726" min="38:45" side="0" fccode="1007" playercode="A08541" score="64-75"/><film id="727" min="38:45" side="1" fccode="1006" playercode="A42652" score="64-75"/><film id="728" fccode="1100" min="39:00" score="64-75"/><film id="729" min="39:00" side="0" fccode="1011" in="A55148" out="A08541" score="64-75"/><film id="730" min="39:00" side="1" fccode="1011" in="8192252" out="A46327" score="64-75"/><film id="731" fccode="1100" min="39:15" score="64-75"/><film id="732" min="39:15" side="1" fccode="1000" playercode="A17053" shottype="2" x="75" y="55" score="64-77"/><film id="733" fccode="1100" min="39:30" score="64-77"/><film id="734" min="39:30" side="0" fccode="1000" playercode="A14098" shottype="1" x="104" y="334" score="66-77"/><film id="735" min="39:30" side="0" fccode="1007" playercode="A43627" score="66-77"/><film id="736" min="39:30" side="1" fccode="1006" playercode="A17053" score="66-77"/><film id="737" min="39:30" side="0" fccode="1011" in="A59187" out="A36553" score="66-77"/><film id="738" min="39:30" side="0" fccode="1011" in="A59188" out="A14098" score="66-77"/><film id="739" min="39:30" side="1" fccode="1000" playercode="A17053" shottype="4" x="0" y="0" score="66-78"/><film id="740" min="39:30" side="1" fccode="1000" playercode="A17053" shottype="4" x="0" y="0" score="66-79"/><film id="741" min="39:30" side="0" fccode="1011" in="A55177" out="A43627" score="66-79"/><film id="742" fccode="1100" min="39:45" score="66-79"/><film id="743" min="39:45" side="1" fccode="1001" playercode="A03385" shottype="2" x="137" y="88" score="66-79"/><film id="744" min="39:45" side="0" fccode="1002" playercode="A59188" score="66-79"/><film id="745" min="39:45" side="0" fccode="1000" playercode="A59187" shottype="1" x="128" y="333" score="68-79"/><film id="746" min="39:45" side="0" fccode="1008" playercode="A49418" score="68-79"/><film id="747" fccode="1100" min="40:00" score="68-79"/><film id="752" fccode="1101" period="4" min="40:00" score="68-79"/></filmlist></fullcourtgame>